pecyn/__init__.py
pecyn/version.py
pecyn-0.2.1.dist-info/LICENSE
pecyn-0.2.1.dist-info/METADATA
pecyn-0.2.1.dist-info/WHEEL
pecyn-0.2.1.dist-info/top_level.txt
pecyn-0.2.1.dist-info/RECORD
